{"note":"Don't delete this file! It's used internally to help with page regeneration.","google":"","name":"MC Dooda","tagline":"My projects","body":"## GitHub projects\r\n\r\n### MyMobADE\r\n[MyMobADE](https://github.com/mcdooda/MyMobADE) provides a mobile-friendly access to ADE, a schedule software used in french universities.\r\n\r\n### Luawie\r\n[Luawie](https://github.com/mcdooda/luawie3) emulates mouse and keyboard input using Wii remotes.\r\nOlder versions can be found on [SourceForge](http://sourceforge.net/projects/luawie/).\r\n\r\n### PiX\r\n[PiX](https://github.com/mcdooda/PiX) is a picross-like game developed in Ruby.\r\n\r\n### BayPHP\r\n[BayPHP](https://github.com/mcdooda/BayPHP) is a PHP implementation of the [BayFiles](http://bayfiles.com) API.\r\n\r\n### Sojourner\r\n[Sojourner](https://github.com/mcdooda/Sojourner) is an experimental project of a game development framework.\r\n\r\n### Lune\r\n[Lune](https://github.com/mcdooda/lune) is an experimental scripting language.\r\n\r\n## Other projects\r\n\r\n### The Guinea Syndrome\r\n[The Guinea Syndrome](http://code.google.com/p/things-get-serious/) (whose code name is Things Get Serious) is a platform game in which an unnamed rabbit has to reach the final carrot using the powers of famous video games heroes.\r\n\r\n### The Global Scourge\r\n[The Global Scourge](http://code.google.com/p/gammapersei/) (whose code name is Gamma Persei) is a real time strategy game in which our primary weapon is a mutating virus.\r\n\r\n### ROFL\r\n[ROFL](https://sourceforge.net/projects/rofl/) is a code name for my next video game project. It will be a Super Smash Bros.-like game including League of Legends heroes."}